[{"id": 4034948, "n": "Utuloa"}, {"id": 7106274, "n": "Sina"}, {"id": 4034977, "n": "Tuamasaga"}, {"id": 4035413, "n": "Apia"}, {"id": 4034894, "n": "Independent State of Samoa"}, {"id": 4034903, "n": "Vaiusu"}, {"id": 4034908, "n": "Vaitele"}, {"id": 4035013, "n": "Solosolo"}, {"id": 4035019, "n": "Siusega"}, {"id": 4035059, "n": "Satapuala"}, {"id": 4035118, "n": "Safotu"}, {"id": 4035174, "n": "Nofoalii"}, {"id": 4035209, "n": "Matavai"}, {"id": 4035236, "n": "Malie"}, {"id": 4035249, "n": "Lufilufi"}, {"id": 4035252, "n": "Lotofaga"}, {"id": 4035260, "n": "Leulumoega"}, {"id": 4035310, "n": "Gataivai"}, {"id": 4035335, "n": "Fasitoouta"}, {"id": 4035345, "n": "Faleula"}, {"id": 4035358, "n": "Falefa"}, {"id": 4035432, "n": "Afenga"}]