[{"id": 174968, "n": "Aygavan"}, {"id": 616053, "n": "Yerazgavors"}, {"id": 616071, "n": "Voskevaz"}, {"id": 616097, "n": "Verin Dvin"}, {"id": 616119, "n": "Vaghashen"}, {"id": 616120, "n": "Vahagni"}, {"id": 616464, "n": "Lukashin"}, {"id": 616492, "n": "Lanjaghbyur"}, {"id": 616523, "n": "Kosh"}, {"id": 616572, "n": "Karchaghbyur"}, {"id": 616576, "n": "Karanlukh"}, {"id": 616668, "n": "Getazat"}, {"id": 616763, "n": "Darpas"}, {"id": 616789, "n": "Bjni"}, {"id": 616791, "n": "Byurakan"}, {"id": 616806, "n": "Bazum"}, {"id": 616828, "n": "Bagratashen"}, {"id": 616853, "n": "Aknalich"}, {"id": 616879, "n": "Ashnak"}, {"id": 616921, "n": "Arevashat"}, {"id": 616954, "n": "Apaga"}, {"id": 616955, "n": "Anushavan"}, {"id": 616981, "n": "Akunk"}, {"id": 617003, "n": "Aghavnadzor"}, {"id": 617027, "n": "Abovyan"}, {"id": 823755, "n": "Artsvaberd"}, {"id": 823791, "n": "Nor Yerznka"}, {"id": 823805, "n": "Lenughi"}, {"id": 823808, "n": "Gay"}, {"id": 866137, "n": "Mrgavet"}, {"id": 866138, "n": "Arevabuyr"}, {"id": 174706, "n": "Yenikend"}, {"id": 616199, "n": "Spitak"}, {"id": 174703, "n": "Zarritap"}, {"id": 174704, "n": "Zangakatun"}, {"id": 174709, "n": "Yeghegnavan"}, {"id": 174713, "n": "Vostan"}, {"id": 174716, "n": "Vernashen"}, {"id": 174717, "n": "Verishen"}, {"id": 174725, "n": "Vedi"}, {"id": 174726, "n": "Vayk"}, {"id": 174743, "n": "Tegh"}, {"id": 174755, "n": "Surenavan"}, {"id": 174764, "n": "Sisavan"}, {"id": 174769, "n": "Shinuhayr"}, {"id": 174775, "n": "Shahumyan"}, {"id": 174776, "n": "Shatin"}, {"id": 174782, "n": "Shaghat"}, {"id": 174794, "n": "Rrind"}, {"id": 174805, "n": "Noyakert"}, {"id": 174820, "n": "Mrgavan"}, {"id": 174828, "n": "Malishka"}, {"id": 174849, "n": "Khndzoresk"}, {"id": 174907, "n": "Getap"}, {"id": 174918, "n": "Dzorastan"}, {"id": 174931, "n": "Dalar"}, {"id": 174940, "n": "Burastan"}, {"id": 174941, "n": "Brun"}, {"id": 174942, "n": "Brrnakot"}, {"id": 174947, "n": "Berkanush"}, {"id": 174964, "n": "Aygezard"}, {"id": 174965, "n": "Aygepat"}, {"id": 174969, "n": "Avshar"}, {"id": 174980, "n": "Yeghegis"}, {"id": 174983, "n": "Armash"}, {"id": 174984, "n": "Areni"}, {"id": 174997, "n": "Angeghakot"}, {"id": 175002, "n": "Aghavnadzor"}, {"id": 175006, "n": "Agarakadzor"}, {"id": 391233, "n": "Aralek"}, {"id": 612561, "n": "Horrom"}, {"id": 613075, "n": "Margara"}, {"id": 616034, "n": "Zovuni"}, {"id": 616037, "n": "Zovaber"}, {"id": 616039, "n": "Zorak"}, {"id": 616046, "n": "Zarr"}, {"id": 616055, "n": "Yeraskhahun"}, {"id": 616056, "n": "Yeranos"}, {"id": 616060, "n": "Yeghegnut"}, {"id": 616061, "n": "Yeghegnut"}, {"id": 616065, "n": "Yeghvard"}, {"id": 616072, "n": "Voskevan"}, {"id": 616076, "n": "Voskehask"}, {"id": 616094, "n": "Verin Getashen"}, {"id": 616100, "n": "Verin Artashat"}, {"id": 616101, "n": "Verin Akhtala"}, {"id": 616103, "n": "Varser"}, {"id": 616108, "n": "Vardenis"}, {"id": 616109, "n": "Vardenik"}, {"id": 616121, "n": "Ushi"}, {"id": 616123, "n": "Urrut"}, {"id": 616136, "n": "Tsovinar"}, {"id": 616137, "n": "Tsovazard"}, {"id": 616138, "n": "Tsovak"}, {"id": 616139, "n": "Tsovagyugh"}, {"id": 616150, "n": "Tsaghkunk"}, {"id": 616158, "n": "Tsaghkahovit"}, {"id": 616159, "n": "Tsaghkaber"}, {"id": 616160, "n": "Tsaghkadzor"}, {"id": 616174, "n": "Tazagyugh"}, {"id": 616184, "n": "Tandzut"}, {"id": 616187, "n": "Talin"}, {"id": 616202, "n": "Spandaryan"}, {"id": 616208, "n": "Sovetakan"}, {"id": 616211, "n": "Solak"}, {"id": 616213, "n": "Sis"}, {"id": 616220, "n": "Shnogh"}, {"id": 616224, "n": "Shirak"}, {"id": 616231, "n": "Shenavan"}, {"id": 616255, "n": "Sarukhan"}, {"id": 616259, "n": "Sarigyugh"}, {"id": 616262, "n": "Saratak"}, {"id": 616265, "n": "Saramech"}, {"id": 616273, "n": "Sarahart"}, {"id": 616278, "n": "Samaghar"}, {"id": 616288, "n": "Ptghni"}, {"id": 616289, "n": "Ptghunk"}, {"id": 616290, "n": "Pshatavan"}, {"id": 616291, "n": "Prroshyan"}, {"id": 616297, "n": "Pokr Mantash"}, {"id": 616299, "n": "Zoravan"}, {"id": 616303, "n": "Pemzashen"}, {"id": 616306, "n": "Parravakar"}, {"id": 616320, "n": "Oshakan"}, {"id": 616328, "n": "Hoktember"}, {"id": 616330, "n": "Odzun"}, {"id": 616340, "n": "Nor Gyugh"}, {"id": 616341, "n": "Nor Geghi"}, {"id": 616345, "n": "Norashen"}, {"id": 616352, "n": "Nor Armavir"}, {"id": 616356, "n": "Noramarg"}, {"id": 616359, "n": "Norakert"}, {"id": 616361, "n": "Noratus"}, {"id": 616375, "n": "Nerkin Getashen"}, {"id": 616383, "n": "Navur"}, {"id": 616385, "n": "Nalbandyan"}, {"id": 616391, "n": "Musayelyan"}, {"id": 616396, "n": "Hovtamej"}, {"id": 616399, "n": "Mrgashen"}, {"id": 616400, "n": "Mrgashat"}, {"id": 616401, "n": "Mrganush"}, {"id": 616403, "n": "Mosesgegh"}, {"id": 616410, "n": "Mets Parni"}, {"id": 616411, "n": "Mets Masrik"}, {"id": 616412, "n": "Mets Mantash"}, {"id": 616416, "n": "Metsavan"}, {"id": 616418, "n": "Mertsavan"}, {"id": 616421, "n": "Meghrashen"}, {"id": 616424, "n": "Meghradzor"}, {"id": 616429, "n": "Mayakovski"}, {"id": 616441, "n": "Marmarashen"}, {"id": 616442, "n": "Marmashen"}, {"id": 616445, "n": "Margahovit"}, {"id": 616453, "n": "Mayisyan"}, {"id": 616456, "n": "Madina"}, {"id": 616465, "n": "Lorut"}, {"id": 616471, "n": "Lichk"}, {"id": 616474, "n": "Lernavan"}, {"id": 616476, "n": "Lerrnapat"}, {"id": 616480, "n": "Lerrnanist"}, {"id": 616481, "n": "Lerrnakert"}, {"id": 616484, "n": "Khoronk"}, {"id": 616488, "n": "Lchashen"}, {"id": 616489, "n": "Lchap"}, {"id": 616522, "n": "Kotayk"}, {"id": 616535, "n": "Hnaberd"}, {"id": 616537, "n": "Khashtarrak"}, {"id": 616554, "n": "Kasakh"}, {"id": 616573, "n": "Karbi"}, {"id": 616590, "n": "Kaputan"}, {"id": 616593, "n": "Kanakerravan"}, {"id": 616598, "n": "Kamo"}, {"id": 616617, "n": "Zhdanov"}, {"id": 616620, "n": "Shahumyan"}, {"id": 616632, "n": "Hayanist"}, {"id": 616634, "n": "Haghartsin"}, {"id": 616639, "n": "Gyulagarak"}, {"id": 616645, "n": "Ghukasavan"}, {"id": 616646, "n": "Geghamasar"}, {"id": 616648, "n": "Gugark"}, {"id": 616650, "n": "Tsiatsan"}, {"id": 616657, "n": "Goght"}, {"id": 616659, "n": "Gogaran"}, {"id": 616669, "n": "Getashen"}, {"id": 616682, "n": "Geghanist"}, {"id": 616692, "n": "Geghamavan"}, {"id": 616697, "n": "Garrni"}, {"id": 616699, "n": "Gagarin"}, {"id": 616701, "n": "Fantan"}, {"id": 616702, "n": "Fioletovo"}, {"id": 616716, "n": "Dzoragyugh"}, {"id": 616719, "n": "Dzithankov"}, {"id": 616722, "n": "Jrashen"}, {"id": 616729, "n": "Jrahovit"}, {"id": 616735, "n": "Janfida"}, {"id": 616741, "n": "Dvin"}, {"id": 616744, "n": "Drakhtik"}, {"id": 616748, "n": "Doghs"}, {"id": 616757, "n": "Ddmashen"}, {"id": 616769, "n": "Dalarik"}, {"id": 616773, "n": "Chochkan"}, {"id": 616792, "n": "Buzhakan"}, {"id": 616822, "n": "Byuravan"}, {"id": 616823, "n": "Bambakashat"}, {"id": 616824, "n": "Balahovit"}, {"id": 616835, "n": "Azatan"}, {"id": 616844, "n": "Haykavan"}, {"id": 616849, "n": "Aygestan"}, {"id": 616850, "n": "Aygeshat"}, {"id": 616851, "n": "Aygeshat"}, {"id": 616855, "n": "Aygehovit"}, {"id": 616872, "n": "Artimet"}, {"id": 616874, "n": "Astghadzor"}, {"id": 616882, "n": "Arzakan"}, {"id": 616888, "n": "Arteni"}, {"id": 616898, "n": "Arshaluys"}, {"id": 616902, "n": "Armavir"}, {"id": 616912, "n": "Argel"}, {"id": 616913, "n": "Argavand"}, {"id": 616914, "n": "Argavand"}, {"id": 616915, "n": "Arevshat"}, {"id": 616916, "n": "Arevshat"}, {"id": 616918, "n": "Arevik"}, {"id": 616920, "n": "Arevashogh"}, {"id": 616931, "n": "Archis"}, {"id": 616933, "n": "Arazap"}, {"id": 616935, "n": "Arrapi"}, {"id": 616936, "n": "Aramus"}, {"id": 616938, "n": "Araks"}, {"id": 616944, "n": "Aragats"}, {"id": 616982, "n": "Akunk"}, {"id": 616989, "n": "Akhuryan"}, {"id": 617002, "n": "Aghavnatun"}, {"id": 617018, "n": "Agarak"}, {"id": 617019, "n": "Agarak"}, {"id": 793638, "n": "Vardablur"}, {"id": 793672, "n": "Bartsrashen"}, {"id": 793693, "n": "Nshavan"}, {"id": 799614, "n": "Norabats"}, {"id": 823723, "n": "Berdavan"}, {"id": 823745, "n": "Shirakamut"}, {"id": 823748, "n": "Azatamut"}, {"id": 823749, "n": "Getahovit"}, {"id": 823793, "n": "Nor Sasunik"}, {"id": 823797, "n": "Kamaris"}, {"id": 823800, "n": "Gandzak"}, {"id": 823802, "n": "Myasnikyan"}, {"id": 823807, "n": "Metsamor"}, {"id": 823809, "n": "Baghramyan"}, {"id": 823810, "n": "Musalerr"}, {"id": 823811, "n": "Darakert"}, {"id": 823812, "n": "Dashtavan"}, {"id": 823813, "n": "Nizami"}, {"id": 823818, "n": "Artsvanist"}, {"id": 859714, "n": "Vardadzor"}, {"id": 866081, "n": "Taronik"}, {"id": 866089, "n": "Aknashen"}, {"id": 866090, "n": "Haykashen"}, {"id": 866091, "n": "Hovtashat"}, {"id": 866092, "n": "Sayat-Nova"}, {"id": 866093, "n": "Voskehat"}, {"id": 866095, "n": "Griboyedov"}, {"id": 866097, "n": "Amberd"}, {"id": 866098, "n": "Aygek"}, {"id": 866134, "n": "Hovtashen"}, {"id": 866135, "n": "Dimitrov"}, {"id": 828260, "n": "Armaviri Marz"}, {"id": 616417, "n": "Metsamor"}, {"id": 174714, "n": "Vosketap"}, {"id": 174982, "n": "Republic of Armenia"}, {"id": 174979, "n": "Artashat"}, {"id": 616051, "n": "Yerevan"}, {"id": 616052, "n": "Yerevan"}, {"id": 828262, "n": "Kotayk\u2019i Marz"}, {"id": 617026, "n": "Abovyan"}, {"id": 409313, "n": "Ararati Marz"}, {"id": 828263, "n": "Lorru Marz"}, {"id": 616530, "n": "Vanadzor"}, {"id": 616629, "n": "Hrazdan"}, {"id": 828264, "n": "Shiraki Marz"}, {"id": 616971, "n": "Amasia"}, {"id": 823816, "n": "Masis"}, {"id": 616724, "n": "Jrashen"}, {"id": 409314, "n": "Syunik\u2019i Marz"}, {"id": 175007, "n": "Agarak"}, {"id": 174875, "n": "Kapan"}, {"id": 174895, "n": "Goris"}, {"id": 616790, "n": "Byureghavan"}, {"id": 828261, "n": "Geghark\u2019unik\u2019i Marz"}, {"id": 616117, "n": "Vahan"}, {"id": 616599, "n": "Gavarr"}, {"id": 828265, "n": "Tavushi Marz"}, {"id": 616627, "n": "Ijevan"}, {"id": 616635, "n": "Gyumri"}, {"id": 174812, "n": "Nerk\u2019in Kamarlu"}, {"id": 616350, "n": "Norashen"}, {"id": 616786, "n": "Chambarak"}, {"id": 174823, "n": "Meghri"}, {"id": 616446, "n": "Maralik"}, {"id": 828259, "n": "Aragatsotni Marz"}, {"id": 616953, "n": "Aparan"}, {"id": 616178, "n": "Tashir"}, {"id": 616974, "n": "Alaverdi"}, {"id": 616479, "n": "Spitak"}, {"id": 616655, "n": "Gomadzor"}, {"id": 616438, "n": "Martuni"}, {"id": 866096, "n": "Echmiadzin"}, {"id": 409315, "n": "Vayots\u2019 Dzori Marz"}, {"id": 174904, "n": "Gladzor"}, {"id": 616742, "n": "Dsegh"}, {"id": 793702, "n": "Verin Jrashen"}, {"id": 616353, "n": "Nor Aresh"}, {"id": 174710, "n": "Yeghegnadzor"}, {"id": 616785, "n": "Ch\u2019arents\u2019avan"}, {"id": 616837, "n": "Azat"}, {"id": 174972, "n": "Hatsavan"}, {"id": 616333, "n": "Noyemberyan"}, {"id": 616752, "n": "Dilijan"}, {"id": 174884, "n": "Jermuk"}, {"id": 616525, "n": "Koghb"}, {"id": 616802, "n": "Berd"}, {"id": 616881, "n": "Arzni"}, {"id": 616230, "n": "Shenavan"}, {"id": 616712, "n": "Dzoraghbyur"}, {"id": 616932, "n": "Arbat"}, {"id": 616917, "n": "Arevik"}, {"id": 174991, "n": "Ararat"}, {"id": 616062, "n": "Ejmiatsin"}, {"id": 616250, "n": "Sevan"}, {"id": 616435, "n": "Masis"}, {"id": 616631, "n": "Armavir"}, {"id": 616877, "n": "Ashtarak"}]